hamlorenz/__init__.py
hamlorenz/hamlorenz.py
hamlorenz-0.1.11.dist-info/licenses/LICENSE
hamlorenz-0.1.11.dist-info/METADATA
hamlorenz-0.1.11.dist-info/WHEEL
hamlorenz-0.1.11.dist-info/top_level.txt
hamlorenz-0.1.11.dist-info/RECORD
