Metadata-Version: 2.4
Name: HamLorenz
Version: 0.1.11
Summary: Hamiltonian Lorenz-like models
Author-email: Cristel Chandre <cristel.chandre@cnrs.fr>
Maintainer-email: Cristel Chandre <cristel.chandre@cnrs.fr>
License: BSD-2-Clause
Project-URL: Homepage, http://github.com/cchandre/HamLorenz
Project-URL: GitHub, http://github.com/cchandre/HamLorenz
Keywords: Lorenz models,Hamiltonian,symplectic integrators
Classifier: Programming Language :: Python :: 3
Classifier: Intended Audience :: Education
Classifier: Intended Audience :: Science/Research
Classifier: Operating System :: OS Independent
Classifier: Topic :: Scientific/Engineering
Classifier: Topic :: Scientific/Engineering :: Mathematics
Classifier: Topic :: Scientific/Engineering :: Chemistry
Classifier: Topic :: Scientific/Engineering :: Physics
Classifier: Topic :: Scientific/Engineering :: Astronomy
Requires-Python: >=3.8
License-File: LICENSE
Requires-Dist: numpy>=1.24.3
Requires-Dist: sympy>=1.11.1
Requires-Dist: pyhamsys>=0.65
Requires-Dist: scipy>=1.11.3
Requires-Dist: pathos>=0.3.4
Requires-Dist: matplotlib>=3.7.2
Dynamic: license-file
